modern_greek_inflexion/__init__.py
modern_greek_inflexion/_version.py
modern_greek_inflexion/exceptions.py
modern_greek_inflexion/adjective/__init__.py
modern_greek_inflexion/adjective/_helpers.py
modern_greek_inflexion/adjective/all/__init__.py
modern_greek_inflexion/adjective/all/create_all_adj.py
modern_greek_inflexion/adjective/all/create_all_alt.py
modern_greek_inflexion/adjective/basic/__init__.py
modern_greek_inflexion/adjective/basic/create_basic_adj.py
modern_greek_inflexion/adverb/__init__.py
modern_greek_inflexion/article/__init__.py
modern_greek_inflexion/noun/__init__.py
modern_greek_inflexion/noun/create_noun_basic.py
modern_greek_inflexion/noun/create_noun_decl.py
modern_greek_inflexion/noun/helpers.py
modern_greek_inflexion/numeral/__init__.py
modern_greek_inflexion/numeral/create_num_decl.py
modern_greek_inflexion/numeral/create_num_list.py
modern_greek_inflexion/pronoun/__init__.py
modern_greek_inflexion/pronoun/create_pron_basic.py
modern_greek_inflexion/pronoun/create_pron_decl.py
modern_greek_inflexion/resources/__init__.py
modern_greek_inflexion/resources/adj.py
modern_greek_inflexion/resources/adv.py
modern_greek_inflexion/resources/article.py
modern_greek_inflexion/resources/noun.py
modern_greek_inflexion/resources/numerals.py
modern_greek_inflexion/resources/prefixes.py
modern_greek_inflexion/resources/pronouns.py
modern_greek_inflexion/resources/typing.py
modern_greek_inflexion/resources/variables.py
modern_greek_inflexion/resources/verb.py
modern_greek_inflexion/resources/lists/__init__.py
modern_greek_inflexion/resources/lists/adj_grammar_lists.pickle
modern_greek_inflexion/resources/lists/el_GR.pickle
modern_greek_inflexion/resources/lists/noun_grammar_lists.pickle
modern_greek_inflexion/resources/lists/nouns_masc_fem.pickle
modern_greek_inflexion/verb/__init__.py
modern_greek_inflexion/verb/helpers.py
modern_greek_inflexion/verb/create/__init__.py
modern_greek_inflexion/verb/create/forms/__init__.py
modern_greek_inflexion-2.0.7.dist-info/AUTHORS
modern_greek_inflexion-2.0.7.dist-info/LICENSE
modern_greek_inflexion-2.0.7.dist-info/METADATA
modern_greek_inflexion-2.0.7.dist-info/WHEEL
modern_greek_inflexion-2.0.7.dist-info/top_level.txt
modern_greek_inflexion-2.0.7.dist-info/RECORD
