Metadata-Version: 2.1
Name: modern-greek-inflexion
Version: 2.0.7
Summary: Python 3 library for creating inflected forms given basic forms of Modern Greek words
Home-page: https://github.com/PicusZeus/modern-greek-inflexion
Author: Krzysztof H
Author-email: krzysztof.hilman@gmail.com
License: MIT
Platform: any
Classifier: Development Status :: 4 - Beta
Classifier: License :: OSI Approved :: MIT License
Classifier: Operating System :: OS Independent
Classifier: Programming Language :: Python :: 3
Classifier: Programming Language :: Python :: 3 :: Only
Classifier: Programming Language :: Python :: 3.9
Classifier: Programming Language :: Python :: 3.10
Classifier: Programming Language :: Python :: 3.11
Classifier: Topic :: Software Development :: Libraries :: Python Modules
Requires-Python: >=3.9
License-File: LICENSE
License-File: AUTHORS
Requires-Dist: modern-greek-accentuation ==1.0.7
Provides-Extra: testing
Requires-Dist: tox >=3.24 ; extra == 'testing'
